ma3xcli/crypto.py
ma3xcli/init_pyenv.py
ma3xcli/ma3xhelp.py
ma3xcli/two.py
ma3xcli-0.1.13.dist-info/entry_points.txt
ma3xcli-0.1.13.dist-info/WHEEL
ma3xcli-0.1.13.dist-info/METADATA
ma3xcli-0.1.13.dist-info/RECORD
